README.md
setup.py
azurebatchmon/__init__.py
azurebatchmon/bwa-alignment-tasks-ubuntu.tsv
azurebatchmon/client_util.py
azurebatchmon/command_maker.py
azurebatchmon/command_maker.pyc
azurebatchmon/hogehoge.sh
azurebatchmon/parser.py
azurebatchmon/run.py
azurebatchmon/task.py
azurebatchmon/task.pyc
azurebatchmon/task_parser.py
azurebatchmon/task_parser.pyc
azurebatchmon/test_main.py
azurebatchmon.egg-info/PKG-INFO
azurebatchmon.egg-info/SOURCES.txt
azurebatchmon.egg-info/dependency_links.txt
azurebatchmon.egg-info/entry_points.txt
azurebatchmon.egg-info/requires.txt
azurebatchmon.egg-info/top_level.txt
azurebatchmon/common/__init__.py
azurebatchmon/common/helpers.py