Metadata-Version: 1.1
Name: azurebatchmon
Version: 0.1.0b2
Summary: Python tools for easy job submission to Azure Batch
Home-page: https://github.com/Genomon-Project/azurebatchmon
Author: Kenichi Chiba and Yuichi Shiraishi
Author-email: genomon.devel@gamil.com
License: GPLv3
Platform: UNKNOWN
Classifier: Development Status :: 4 - Beta
Classifier: Intended Audience :: Science/Research
Classifier: License :: OSI Approved :: GNU General Public License v3 (GPLv3)
Classifier: Operating System :: Unix
Classifier: Programming Language :: Python :: 2.7
Classifier: Topic :: Scientific/Engineering :: Bio-Informatics
